CToolKit/ComandLineExecution.py
CToolKit/__init__.py
CToolKit/amalgamation.py
CToolKit/comand_line_functions.py
CToolKit/output_formatation.py
CToolKit/readme_converter.py
CToolKit/valgrind_parser.py
CToolKit/Errors/ComandLineError.py
CToolKit/Errors/ComandLineWarning.py
CToolKit/Errors/CopilationError.py
CToolKit/Errors/CopilationWarning.py
CToolKit/Errors/ExecutionError.py
CToolKit/Errors/NotExpectedResult.py
CToolKit/Errors/ValgrindError.py
CToolKit/Errors/ValgrindLeak.py
CToolKit/Errors/__init__.py
CToolKit-1.20.dist-info/LICENSE
CToolKit-1.20.dist-info/METADATA
CToolKit-1.20.dist-info/WHEEL
CToolKit-1.20.dist-info/top_level.txt
CToolKit-1.20.dist-info/RECORD
